Metadata-Version: 1.1
Name: event-simulate
Version: 1.1.1
Summary: 模拟键盘,鼠标事件的Python包。可用于编写自动化程序 (如游戏外挂)。A Python package simulating keyboard and mouse events ,which can be used in automation programs.
Home-page: https://github.com/qfcy/Python/tree/main/event
Author: 七分诚意 qq:3076711200
Author-email: 3076711200@qq.com
License: UNKNOWN
Keywords: event,simulate,key,mouse,click,automation,键盘,鼠标,外挂
Platform: UNKNOWN
Classifier: Programming Language :: Python :: 3
Classifier: Natural Language :: Chinese (Simplified)
Classifier: Environment :: Win32 (MS Windows)
Classifier: Topic :: Desktop Environment :: Window Managers :: Blackbox
Classifier: Topic :: Desktop Environment :: Window Managers
Classifier: Topic :: Desktop Environment :: Window Managers :: Applets
Classifier: Topic :: Education
Classifier: Topic :: Utilities
